django_cryptolock/__init__.py
django_cryptolock/apps.py
django_cryptolock/backends.py
django_cryptolock/forms.py
django_cryptolock/models.py
django_cryptolock/urls.py
django_cryptolock/utils.py
django_cryptolock/validators.py
django_cryptolock/views.py
django_cryptolock/migrations/0001_initial.py
django_cryptolock/migrations/0002_auto_20200218_1312.py
django_cryptolock/migrations/__init__.py
django_cryptolock/static/css/django_cryptolock.css
django_cryptolock/static/js/django_cryptolock.js
django_cryptolock/templates/django_cryptolock/base.html
django_cryptolock-0.1.0.dist-info/DESCRIPTION.rst
django_cryptolock-0.1.0.dist-info/METADATA
django_cryptolock-0.1.0.dist-info/RECORD
django_cryptolock-0.1.0.dist-info/WHEEL
django_cryptolock-0.1.0.dist-info/metadata.json
django_cryptolock-0.1.0.dist-info/top_level.txt
