Metadata-Version: 2.0
Name: django-cryptolock
Version: 0.1.0
Summary: Django authentication using cryptocurrency wallets
Home-page: https://github.com/dethos/django-cryptolock
Author: Gonçalo Valério
Author-email: gon@ovalerio.net
License: MIT
Keywords: django-cryptolock
Platform: UNKNOWN
Classifier: Development Status :: 3 - Alpha
Classifier: Framework :: Django :: 2.2
Classifier: Framework :: Django :: 3.0
Classifier: Intended Audience :: Developers
Classifier: License :: OSI Approved :: MIT License
Classifier: Natural Language :: English
Classifier: Programming Language :: Python :: 3
Classifier: Programming Language :: Python :: 3.6
Classifier: Programming Language :: Python :: 3.7
Classifier: Programming Language :: Python :: 3.8
Requires-Dist: django (>=2.2)
Requires-Dist: django-model-utils (>=2.0)
Requires-Dist: monero (>=0.6)
Requires-Dist: python-monerorpc (>=0.5.5)
Requires-Dist: pybitid (>=0.0.4)
